[
    {
        "name": "Home",
        "link": "index.wiki",
        "icon": "fa fa-home",
        "subMenu": []
    },
    {
        "name": "Project",
        "link": "project.wiki",
        "icon": "fa fa-lightbulb-o",
        "subMenu": []
    },
    {
        "name": "Dynamic Applications",
        "link": "dynamic_applications.wiki",
        "icon": "fa fa-bolt",
        "subMenu": []
    },
    {
        "name": "Architecture",
        "link": "architecture.wiki",
        "icon": "fa fa-building-o",
        "subMenu": []
    },
    {
        "name": "API",
        "link": "api.wiki",
        "icon": "fa fa-sitemap",
        "subMenu": []
    },
    {
        "name": "License",
        "link": "license.wiki",
        "icon": "fa fa-info",
        "subMenu": []
    },
    {
        "name": "Credits",
        "link": "credits.wiki",
        "icon": "fa fa-film",
        "subMenu": []
    },
    {
        "name": "Features",
        "link": "features.wiki",
        "icon": "fa fa-info",
        "subMenu": [
            {
                "name": "Features",
                "link": "features.wiki",
                "icon": "fa fa-home"
            },
            {
                "name": "Data Structures",
                "link": "data_structures.wiki",
                "icon": "fa fa-table"
            },
            {
                "name": "Extension Definitions",
                "link": "extension_definitions.wiki",
                "icon": "fa fa-external-link"
            },
            {
                "name": "Scripting Services",
                "link": "scripting_services.wiki",
                "icon": "fa fa-pencil-square-o"
            },
            {
                "name": "Integration Services",
                "link": "integration_services.wiki",
                "icon": "fa fa-puzzle-piece"
            },
            {
                "name": "Test Cases",
                "link": "test_cases.wiki",
                "icon": "fa fa-flask"
            },
            {
                "name": "Web Content",
                "link": "web_content.wiki",
                "icon": "fa fa-globe"
            },
            {
                "name": "Wiki Content",
                "link": "wiki_content.wiki",
                "icon": "fa fa-quote-right"
            },
            {
                "name": "Security",
                "link": "security.wiki",
                "icon": "fa fa-shield"
            },
            {
                "name": "Registry",
                "link": "registry.wiki",
                "icon": "fa fa-picture-o"
            },
            {
                "name": "Git Integration",
                "link": "git.wiki",
                "icon": "fa fa-github"
            },
            {
                "name": "Debugger",
                "link": "debugger.wiki",
                "icon": "fa fa-wrench"
            },
            {
                "name": "Backup",
                "link": "backup.wiki",
                "icon": "fa fa-floppy-o"
            }
        ]
    },
    {
        "name": "Concepts",
        "icon": "fa fa-info",
        "subMenu": [
            {
                "name": "Concepts",
                "link": "concepts.wiki",
                "icon": "fa fa-cogs"
            },
            {
                "name": "Workspace",
                "link": "workspace.wiki",
                "icon": "fa fa-desktop"
            },
            {
                "name": "Activation",
                "link": "activation.wiki",
                "icon": "fa fa-sign-in"
            },
            {
                "name": "Publishing",
                "link": "publishing.wiki",
                "icon": "fa fa-upload"
            },
            {
                "name": "Generation",
                "link": "generation.wiki",
                "icon": "fa fa-cog"
            },
            {
                "name": "Entity Service",
                "link": "entity_service.wiki",
                "icon": "fa fa-retweet"
            }
        ]
    },
    {
        "name": "Tooling",
        "link": "tooling.wiki",
        "icon": "fa fa-gavel",
        "subMenu": []
    },
    {
        "name": "Perspectives",
        "icon": "fa fa-info",
        "subMenu": [
            {
                "name": "Workspace",
                "link": "workspace_perspective.wiki",
                "icon": "fa fa-desktop"
            },
            {
                "name": "Database",
                "link": "database_perspective.wiki",
                "icon": "fa fa-th-large"
            },
            {
                "name": "Repository",
                "link": "repository_perspective.wiki",
                "icon": "fa fa-inbox"
            },
            {
                "name": "Registry",
                "link": "registry.wiki",
                "icon": "fa fa-picture-o"
            },
            {
                "name": "Debug",
                "link": "debugger.wiki",
                "icon": "fa fa-wrench"
            }
        ]
    },
    {
        "name": "Editors and Views",
        "icon": "fa fa-info",
        "subMenu": [
            {
                "name": "Source Editor",
                "link": "source_editor.wiki",
                "icon": "fa fa-code"
            },
            {
                "name": "SQL Console",
                "link": "sql_console.wiki",
                "icon": "fa fa-terminal"
            },
            {
                "name": "Log Viewer",
                "link": "log_viewer.wiki",
                "icon": "fa fa-tags"
            }
        ]
    },
    {
        "name": "Services",
        "icon": "fa fa-info",
        "subMenu": [
            {
                "name": "Services",
                "link": "services_runtime.wiki",
                "icon": "fa fa-home"
            },
            {
                "name": "Operational",
                "link": "service_operational.wiki",
                "icon": "fa fa-tachometer"
            },
            {
                "name": "Memory",
                "link": "service_memory.wiki",
                "icon": "fa fa-bar-chart-o"
            },
            {
                "name": "Search",
                "link": "service_search.wiki",
                "icon": "fa fa-search"
            },
            {
                "name": "Logging",
                "link": "service_logging.wiki",
                "icon": "fa fa-video-camera"
            },
            {
                "name": "Access Log",
                "link": "service_accesslog.wiki",
                "icon": "fa fa-key"
            },
            {
                "name": "Repository",
                "link": "service_repository.wiki",
                "icon": "fa fa-inbox"
            }
        ]
    },
    {
        "navigation_right": [
            {
                "name": "Project",
                "link": "../../web/welcome/index.html",
                "icon": "fa fa-play-circle",
                "subMenu": []
            },
            {
                "name": "Samples",
                "link": "../samples/index.wiki",
                "icon": "fa fa-gift",
                "subMenu": []
            }
        ]
    }
]
